[
    {
        "author": "AMediocreWhiteGuy",
        "body": "Mine is General Electric and Hewlett-Packard",
        "created_utc": 1621367784,
        "id": "gylynaj",
        "score": 9,
        "subreddit": "stocks",
        "created": 1621396584.0
    },
    {
        "author": "Robot_of_Sherwood",
        "body": "# Today is Wednesday, the 26th of May\n\n\n\n## Upcoming events for Wednesday, May 26th\n\n - Stock splits:\n\n    - UVXY @ **1:10**\n    - VIXY @ **1:4**\n    - SCO @ **1:4**\n    - ZSL @ **1:4**\n\n - Expected earnings:\n\n  AEO, AGL, ANF, APPS, BBAR, BBW, BLRX, BMO, BORR, BQ, CHNG, CLGN, CMCO, CMRE, CPRI, CRKN, CVCO, DBI, DKS, DXC, ELF, EVGN, FRO, GASS, GOTU, GRIN, HLG, HMG, HOTH, ICLK, LAIX, LAZY, LI, MESO, MOD, NESR, NFH, NTNX, NVDA, NVIV, NXGN, OKTA, OOMA, PDD, PLAB, PSTG, PTNR, QADA, QADB, QMCO, REX, SFET, SINT, SJ, SNOW, TYME, UCL, UHAL, UVV, VTOL, VTRU, WDAY, WSM, ZUO\n\n - Ex-div:\n\n  ACCO, AMAT, AVA, B, CHE, CTB, DAC, FWRD, IP, JBT, KNSL, MTRN, PSEC, SMG, XYL\n\n - Economic events and announcements:\n\n    - 5-Year Note Auction (previous: 0.849%)\n    - Crude Oil Imports (previous: -0.587M)\n    - Crude Oil Inventories (consensus: -1.050M, previous: 1.321M)\n    - Cushing Crude Oil Inventories (previous: -0.142M)\n    - Distillate Fuel Production (previous: -0.102M)\n    - EIA Refinery Crude Runs  (previous: 0.096M)\n    - EIA Weekly Distillates Stocks (consensus: -1.900M, previous: -2.324M)\n    - EIA Weekly Refinery Utilization Rates (consensus: 0.2%, previous: 0.2%)\n    - FOMC Member Quarles Speaks\n    - FOMC Member Quarles Speaks\n    - Gasoline Inventories (consensus: -0.614M, previous: -1.963M)\n    - Gasoline Production (previous: 0.165M)\n    - Heating Oil Stockpiles (previous: -0.164M)\n    - MBA 30-Year Mortgage Rate (previous: 3.15%)\n    - MBA Mortgage Applications (previous: 1.2%)\n    - MBA Purchase Index (previous: 265.3)\n    - Mortgage Market Index (previous: 724.2)\n    - Mortgage Refinance Index (previous: 3,413.3)\n\n## Upcoming events for Thursday, May 27th\n\n - Expected earnings:\n\n  ADIL, ADSK, AFYA, AMWD, APOP, ASND, ATHM, BBY, BOSC, BOX, BURL, CCEP, CDZI, CELC, CETX, CIH, CKX, CM, CNF, COST, CRM, CRVL, DELL, DG, DLTR, DOMO, DYAI, EBR, EBR.B, FANH, FRSX, GCO, GES, GNPX, GPS, HHR, HLNE, HMLP, HPQ, JOBS, KRT, LBPS, LGF.A, LGF.B, LIZI, MACK, MANU, MDT, MIXT, MOMO, MOV, MYSZ, NUZE, NVGS, OLLI, PBR.A, PLAN, PLUG, PRVA, QFIN, RDHL, RY, RYB, SAFM, SBR, SBSW, SEEL, SKM, SPCB, SUPV, TD, TDAC, THR, TITN, ULTA, VEEV, VIOT, VMW, YEXT, YJ, YTRA, YY\n\n - Ex-div:\n\n  ABTX, ADC, ADI, AGNC, ALTM, ALV, AVAL, AY, BEPC, BIPC, BMI, BOH, BRMK, CATY, CBT, CFR, CPF, CR, CRT, CSX, CTT, DD, DNP, DOV, DOW, EAF, EFC, EL, EQH, EVR, FBHS, FT, FTV, FXNC, GLW, HII, HQH, HUBB, J, JKHY, KHC, KINS, MAIN, MARPS, MAS, MKSI, MLAB, MLHR, MTR, NBHC, NNI, NUS, NWL, ORC, PBT, PDM, PFIS, PIPR, POWI, PRT, PTVE, RLI, RS, SBLK, SCL, SCM, SGC, SJT, SLG, STAG, STE, STRA, TNC, TSLX, TV, UBOH, UG, UNP, VMC, VVV, WEYS, WHD, WLTW, YUM\n\n - Economic events and announcements:\n\n    - 4-Week Bill Auction (previous: 0.000%)\n    - 7-Year Note Auction (previous: 1.306%)\n    - 8-Week Bill Auction (previous: 0.005%)\n    - Continuing Jobless Claims (consensus: 3,680K, previous: 3,751K)\n    - Core Durable Goods Orders (consensus: 0.8%, previous: 2.3%)\n    - Core PCE Prices (consensus: 2.30%, previous: 2.30%)\n    - Corporate Profits (previous: 27.0%)\n    - Durable Goods Orders (consensus: 0.7%, previous: 1.0%)\n    - Durables Excluding Defense (previous: 1.8%)\n    - GDP (consensus: 6.5%, previous: 6.4%)\n    - GDP Price Index (consensus: 4.1%, previous: 4.1%)\n    - GDP Sales (previous: 9.2%)\n    - Goods Orders Non Defense Ex Air (consensus: 0.8%, previous: 1.0%)\n    - Initial Jobless Claims (consensus: 425K, previous: 444K)\n    - Jobless Claims 4-Week Avg. (previous: 504.75K)\n    - KC Fed Composite Index (previous: 31)\n    - KC Fed Manufacturing Index (previous: 40)\n    - Natural Gas Storage (previous: 71B)\n    - PCE Prices (previous: 3.5%)\n    - Pending Home Sales (consensus: 0.8%, previous: 1.9%)\n    - Pending Home Sales Index (previous: 111.3)\n    - Real Consumer Spending (previous: 10.7%)\n\n## Upcoming events for Friday, May 28th\n\n - Expected earnings:\n\n  ANAT, AZRX, BCOW, BIG, BPYU, CAL, CBLI, CIG, GB, GTT, GWGH, HIBB, HUSA, MARPS, MBOT, MDLY, MDNA, MLND, MOGU, MTR, MYMD, OGEN, PALI, PRT, SQBG, XPL\n\n - Ex-div:\n\n  ACNB, AIZ, ASB, ASH, BCC, BGFV, BLL, BRKR, BWA, CABO, CCNE, COWN, CRD.A, CRD.B, CWEN, CWEN.A, CXP, EBAY, EMCF, ESCA, ESI, ESNT, EXPD, FBC, FF, FFBC, FNB, FNCB, GBL, GCMG, GPI, GS, HAYN, HBB, HIG, HQI, HVT, HVT.A, HY, IBKR, IEP, INFY, JNPR, K, KEY, LCNB, LHX, LMT, LUMN, LZB, MAN, MCD, MGEE, MLM, MOFG, MTB, MVBF, NBTB, NC, NETI, NFE, NGVC, NKE, NOC, NTST, O, ONB, PANL, PATK, PII, PINC, PRGS, SAFT, SBGI, SF, SLGN, SPKE, SSNC, STAR, TRMK, TSN, TW, UFPI, VIRT, WEN, WMS, WTS, ZEUS\n\n - Economic events and announcements:\n\n    - CFTC Aluminium speculative net positions (previous: 3.2K)\n    - CFTC Copper speculative net positions (previous: 39.0K)\n    - CFTC Corn speculative net positions (previous: 459.5K)\n    - CFTC Crude Oil speculative net positions (previous: 475.9K)\n    - CFTC Gold speculative net positions (previous: 198.9K)\n    - CFTC Nasdaq 100 speculative net positions (previous: -6.1K)\n    - CFTC Natural Gas speculative net positions (previous: -68.8K)\n    - CFTC S&amp;P 500 speculative net positions (previous: -23.2K)\n    - CFTC Silver speculative net positions (previous: 51.0K)\n    - CFTC Soybeans speculative net positions (previous: 228.3K)\n    - CFTC Wheat speculative net positions (previous: 25.7K)\n    - Chicago PMI (consensus: 68.0, previous: 72.1)\n    - Core PCE Price Index (consensus: 0.6%, previous: 0.4%)\n    - Core PCE Price Index (consensus: 2.9%, previous: 1.8%)\n    - Dallas Fed PCE (previous: 2.00%)\n    - Goods Trade Balance (previous: -90.60B)\n    - Michigan 5-Year Inflation Expectations (previous: 3.10%)\n    - Michigan Consumer Expectations (previous: 77.6)\n    - Michigan Consumer Sentiment (consensus: 82.9, previous: 82.8)\n    - Michigan Current Conditions (previous: 90.8)\n    - Michigan Inflation Expectations (previous: 4.6%)\n    - PCE Price index (previous: 2.3)\n    - PCE price index (previous: 0.5%)\n    - Personal Income (consensus: -14.1%, previous: 21.1%)\n    - Personal Spending (consensus: 0.5%, previous: 4.2%)\n    - Real Personal Consumption (previous: 3.6%)\n    - Retail Inventories Ex Auto (previous: 0.6%)\n    - U.S. Baker Hughes Oil Rig Count (previous: 352)\n    - U.S. Baker Hughes Total Rig Count (previous: 453)\n    - Wholesale Inventories (previous: 1.3%)\n\n^^^^2021-05-26",
        "created_utc": 1622023214,
        "id": "gzhvnhk",
        "score": 6,
        "subreddit": "RobinHood",
        "created": 1622052014.0
    },
    {
        "author": "SkywingMasters",
        "body": "I love watching you retards chase the dragon on dogshit companies, when the boring old boomers at /r/investing are up 50% YTD on boring ass stocks like XOM and HPQ.",
        "created_utc": 1620317594,
        "id": "gx5yd3o",
        "score": 6,
        "subreddit": "wallstreetbets",
        "created": 1620346394.0
    },
    {
        "author": "YourFriendlyUncle",
        "body": "Yeah these comments in here are pretty much straight up garbage.\n\n I would put 15,000-17,500 into either a global ETF like XEQT or VEQT, OR make your own balance for different market ETFs with which market you think will do best (I have an extra weight into US total and S&amp;P for example).\n\nGet 1-3 specific Bluechip companies you think are healthy /support (like if you shop at Crappy Tire buy CTC-A, I dunno). Leave like 500-$1000 for some play/gambling spec plays. I have like 2-2.5% of my portfolio spread between HPQ, GRN, and PYR as spec stocks I believe in",
        "created_utc": 1620670746,
        "id": "gxmx7x1",
        "score": 5,
        "subreddit": "CanadianInvestor",
        "created": 1620699546.0
    },
    {
        "author": "Mack_Guyver",
        "body": "Excellent day for HPQ",
        "created_utc": 1620340822,
        "id": "gx7hof9",
        "score": 5,
        "subreddit": "CanadianInvestor",
        "created": 1620369622.0
    },
    {
        "author": "kavinskys",
        "body": "Any day that HPQ is up is a good day. This is a good stock.",
        "created_utc": 1621540439,
        "id": "gyv1phs",
        "score": 5,
        "subreddit": "CanadianInvestor",
        "created": 1621569239.0
    },
    {
        "author": "Ironleg01",
        "body": "Ok, I'll start. I think HPE is overlooked. I think people have this perception that HPE makes PCs and printers (no, that's HPQ). I got in at $9 and I think long term there is still much more room for price to appreciate.",
        "created_utc": 1621872622,
        "id": "gzabc9p",
        "score": 4,
        "subreddit": "stocks",
        "created": 1621901422.0
    },
    {
        "author": "InMyFeelins",
        "body": "What happened to HPQ in the last part of the day? It\u2019s a welcome spike from the constant slow bleeding of the past month",
        "created_utc": 1620331901,
        "id": "gx6wxw6",
        "score": 4,
        "subreddit": "CanadianInvestor",
        "created": 1620360701.0
    },
    {
        "author": "M--P",
        "body": "HPQ",
        "created_utc": 1621515036,
        "id": "gytel13",
        "score": 4,
        "subreddit": "stocks",
        "created": 1621543836.0
    },
    {
        "author": "kavinskys",
        "body": "HPQ.",
        "created_utc": 1620338815,
        "id": "gx7dboo",
        "score": 3,
        "subreddit": "CanadianInvestor",
        "created": 1620367615.0
    },
    {
        "author": "YourFriendlyUncle",
        "body": "Who needs blue chips when there's hype speculatives! \n\nHPQ and PYR are hella sexy I had PYR @$3 jumped the shark and sold before it hit $12 :(",
        "created_utc": 1620267713,
        "id": "gx3s9wk",
        "score": 3,
        "subreddit": "CanadianInvestor",
        "created": 1620296513.0
    },
    {
        "author": "knuckl3dragg3r",
        "body": "I'll second that. I was riding free shares of HPQ after my initial position doubled and I cashed out half. Made the mistake of selling remainder at 26ish and have continued watching it climb 35+ and shaking my head...",
        "created_utc": 1620324578,
        "id": "gx6f7je",
        "score": 3,
        "subreddit": "wallstreetbets",
        "created": 1620353378.0
    },
    {
        "author": "Coffeepillow",
        "body": "Sold some CCs on HPQ expiring tomorrow not realizing that the ER was today. It\u2019s a good thing the had a stellar report so the stock went down because that\u2019s the current MO of the market apparently.",
        "created_utc": 1622148731,
        "id": "gzok02d",
        "score": 2,
        "subreddit": "wallstreetbets",
        "created": 1622177531.0
    },
    {
        "author": "aapolitical",
        "body": "HPQ drops in after market after earnings beat expectations.",
        "created_utc": 1622152610,
        "id": "gzoskwc",
        "score": 2,
        "subreddit": "stocks",
        "created": 1622181410.0
    },
    {
        "author": "aapolitical",
        "body": "Anyone buying HPQ today?",
        "created_utc": 1622216385,
        "id": "gzrqdqg",
        "score": 2,
        "subreddit": "stocks",
        "created": 1622245185.0
    },
    {
        "author": "OnlineWithLuke",
        "body": "HPQ Silicon just randomly took off mid day without news",
        "created_utc": 1620323649,
        "id": "gx6cxaw",
        "score": 2,
        "subreddit": "pennystocks",
        "created": 1620352449.0
    },
    {
        "author": "ryry1237",
        "body": "Don't forget old tech (IBM, CSCO, HPQ). Old tech has been outperforming lately.",
        "created_utc": 1621282543,
        "id": "gyhjm1d",
        "score": 2,
        "subreddit": "StockMarket",
        "created": 1621311343.0
    },
    {
        "author": "Robot_of_Sherwood",
        "body": "# Today is Thursday, the 27th of May\n\n\n\n## Upcoming events for Thursday, May 27th\n\n - Expected earnings:\n\n  ADIL, ADSK, AFYA, AMWD, APOP, ASND, ATHM, BBY, BOSC, BOX, BURL, CCEP, CDZI, CELC, CETX, CIH, CKX, CM, CNF, COST, CRM, CRVL, DELL, DG, DLTR, DOMO, DYAI, EBR, EBR.B, FANH, FRO, FRSX, GCO, GES, GNPX, GPS, HHR, HLNE, HMLP, HPQ, JOBS, KRT, LBPS, LGF.A, LGF.B, LMPX, MACK, MANU, MDT, MIXT, MOMO, MOV, MYSZ, NM, NUZE, NVGS, OLLI, PLAN, PLUG, PRVA, QFIN, RDHL, RY, RYB, SAFM, SBSW, SEEL, SKM, SPCB, SUPV, TD, TDAC, THR, TITN, ULTA, VEEV, VIOT, VMW, YEXT, YJ, YTRA, YY\n\n - Ex-div:\n\n  ABTX, ADC, ADI, AGNC, ALTM, ALV, AVAL, AY, BEPC, BIPC, BMI, BOH, BRMK, CATY, CBT, CFR, CPF, CR, CRT, CSX, CTT, DD, DNP, DOV, DOW, EAF, EFC, EL, EQH, EVR, FBHS, FT, FTV, FXNC, GLW, HII, HQH, HUBB, J, JKHY, KHC, KINS, MAIN, MARPS, MAS, MKSI, MLAB, MLHR, MTR, NBHC, NNI, NUS, NWL, ORC, PBT, PDM, PFIS, PIPR, POWI, PRT, PTVE, RLI, RS, SBLK, SCL, SCM, SGC, SJT, SLG, STAG, STE, STRA, TNC, TSLX, TV, UBOH, UG, UNP, VMC, VVV, WEYS, WHD, WLTW, YUM\n\n - Economic events and announcements:\n\n    - 4-Week Bill Auction (previous: 0.000%)\n    - 7-Year Note Auction (previous: 1.306%)\n    - 8-Week Bill Auction (previous: 0.005%)\n    - Continuing Jobless Claims (consensus: 3,680K, previous: 3,751K)\n    - Core Durable Goods Orders (consensus: 0.8%, previous: 2.3%)\n    - Core PCE Prices (consensus: 2.30%, previous: 2.30%)\n    - Corporate Profits (previous: 27.0%)\n    - Durable Goods Orders (consensus: 0.7%, previous: 1.0%)\n    - Durables Excluding Defense (previous: 1.8%)\n    - GDP (consensus: 6.5%, previous: 6.4%)\n    - GDP Price Index (consensus: 4.1%, previous: 4.1%)\n    - GDP Sales (previous: 9.2%)\n    - Goods Orders Non Defense Ex Air (consensus: 0.8%, previous: 1.0%)\n    - Initial Jobless Claims (consensus: 425K, previous: 444K)\n    - Jobless Claims 4-Week Avg. (previous: 504.75K)\n    - KC Fed Composite Index (previous: 31)\n    - KC Fed Manufacturing Index (previous: 40)\n    - Natural Gas Storage (consensus: 104B, previous: 71B)\n    - PCE Prices (previous: 3.5%)\n    - Pending Home Sales (consensus: 0.8%, previous: 1.9%)\n    - Pending Home Sales Index (previous: 111.3)\n    - Real Consumer Spending (previous: 10.7%)\n\n## Upcoming events for Friday, May 28th\n\n - Expected earnings:\n\n  ANAT, AZRX, BIG, BPYU, CAL, CBLI, CIG, GB, GTT, GWGH, HIBB, HUSA, MARPS, MBOT, MDLY, MDNA, MLND, MOGU, MTR, MYMD, OGEN, PALI, SQBG, XPL\n\n - Ex-div:\n\n  ACNB, AIZ, ASB, ASH, BCC, BGFV, BLL, BRKR, BWA, CABO, CCNE, COWN, CRD.A, CRD.B, CWEN, CWEN.A, CXP, EBAY, EMCF, ESCA, ESI, ESNT, EXPD, FBC, FF, FFBC, FNB, FNCB, GBL, GCMG, GPI, GS, HAYN, HBB, HIG, HQI, HVT, HVT.A, HY, IBKR, IEP, INFY, JNPR, K, KEY, LCNB, LHX, LMT, LUMN, LZB, MAN, MCD, MGEE, MLM, MOFG, MTB, MVBF, NBTB, NC, NETI, NFE, NGVC, NKE, NOC, NTST, O, ONB, PANL, PATK, PII, PINC, PRGS, SAFT, SBGI, SF, SLGN, SPKE, SSNC, STAR, TRMK, TSN, TW, UFPI, VIRT, WEN, WMS, WTS, ZEUS\n\n - Economic events and announcements:\n\n    - CFTC Aluminium speculative net positions (previous: 3.2K)\n    - CFTC Copper speculative net positions (previous: 39.0K)\n    - CFTC Corn speculative net positions (previous: 459.5K)\n    - CFTC Crude Oil speculative net positions (previous: 475.9K)\n    - CFTC Gold speculative net positions (previous: 198.9K)\n    - CFTC Nasdaq 100 speculative net positions (previous: -6.1K)\n    - CFTC Natural Gas speculative net positions (previous: -68.8K)\n    - CFTC S&amp;P 500 speculative net positions (previous: -23.2K)\n    - CFTC Silver speculative net positions (previous: 51.0K)\n    - CFTC Soybeans speculative net positions (previous: 228.3K)\n    - CFTC Wheat speculative net positions (previous: 25.7K)\n    - Chicago PMI (consensus: 68.0, previous: 72.1)\n    - Core PCE Price Index (consensus: 0.6%, previous: 0.4%)\n    - Core PCE Price Index (consensus: 2.9%, previous: 1.8%)\n    - Dallas Fed PCE (previous: 2.00%)\n    - Goods Trade Balance (previous: -90.60B)\n    - Michigan 5-Year Inflation Expectations (previous: 3.10%)\n    - Michigan Consumer Expectations (previous: 77.6)\n    - Michigan Consumer Sentiment (consensus: 82.9, previous: 82.8)\n    - Michigan Current Conditions (previous: 90.8)\n    - Michigan Inflation Expectations (previous: 4.6%)\n    - PCE Price index (previous: 2.3)\n    - PCE price index (previous: 0.5%)\n    - Personal Income (consensus: -14.1%, previous: 21.1%)\n    - Personal Spending (consensus: 0.5%, previous: 4.2%)\n    - Real Personal Consumption (previous: 3.6%)\n    - Retail Inventories Ex Auto (previous: 0.6%)\n    - U.S. Baker Hughes Oil Rig Count (previous: 352)\n    - U.S. Baker Hughes Total Rig Count (previous: 453)\n    - Wholesale Inventories (previous: 1.3%)\n\n^^^^2021-05-27",
        "created_utc": 1622109614,
        "id": "gzmb2af",
        "score": 2,
        "subreddit": "RobinHood",
        "created": 1622138414.0
    },
    {
        "author": "Greasyfork",
        "body": "Yep, waiting for that next big catalyst. Give me a partnership or some other crazy thing. Elon Musk should buy hpq for his tesla silica department lol.",
        "created_utc": 1619989164,
        "id": "gwpjpm5",
        "score": 1,
        "subreddit": "pennystocks",
        "created": 1620017964.0
    },
    {
        "author": "get_MEAN_yall",
        "body": "HPQ 29c 7/16s, time to load up",
        "created_utc": 1622213018,
        "id": "gzripoc",
        "score": 1,
        "subreddit": "wallstreetbets",
        "created": 1622241818.0
    },
    {
        "author": "Emergency_Thanks4656",
        "body": "HPQ dip looking pretty juicy right here\n\nI am typing this message from an HP laptop\n\nzoom out they have gone nothing but up since covid",
        "created_utc": 1622220102,
        "id": "gzrz6kw",
        "score": 1,
        "subreddit": "wallstreetbets",
        "created": 1622248902.0
    },
    {
        "author": "Delanorix",
        "body": "HPQ 31c 6/18 \n\nI'm gonna try the whole calls after earnings thing.",
        "created_utc": 1622237850,
        "id": "gzt1yza",
        "score": 1,
        "subreddit": "wallstreetbets",
        "created": 1622266650.0
    },
    {
        "author": "get_MEAN_yall",
        "body": "HPQ, as much as you can afford",
        "created_utc": 1622245506,
        "id": "gztga14",
        "score": 1,
        "subreddit": "wallstreetbets",
        "created": 1622274306.0
    },
    {
        "author": "becavern23",
        "body": "Ahh late to the game on pyr for me, gotta avg down A little after this dip bit hpq just below 1. Gunna be long hauls but I believe in this spec plays",
        "created_utc": 1620267923,
        "id": "gx3soim",
        "score": 1,
        "subreddit": "CanadianInvestor",
        "created": 1620296723.0
    },
    {
        "author": "Walter_Whitewall",
        "body": "Anyone else seeing how cheap HPQ calls are? They beat earnings Thursday, shit the bed 9% Friday and  $30 7/2 calls closed at $0.62. That\u2019s looking like a buy.",
        "created_utc": 1622475049,
        "id": "h039ztn",
        "score": 1,
        "subreddit": "wallstreetbets",
        "created": 1622503849.0
    },
    {
        "author": "PiegeonWP",
        "body": "It's OK to be suspicious but the fact of the matter is China Rapid Finance was a real company and listed on the NYSE for years. After approval from shareholders, the decision was made to change the name to SOS Limited, better aligning with the core business and  parent company. \n\nA few key names helping the case for SOS....\n\nRussell Krauss - Vice Chair, Board Member.\n ** I won't provide the link to his LinkedIn page. You are all free to check that yourself. However, he was an executive at Hewlett Packard for many years. Also previous ties to Westinghouse and Electronic Data Systems.\n\nDouglas Brown - Independent, Non Executive Director\n**Former Morgan Stanley executive for years and now part of the Transamerica leadership team. He is listed on their official site and as part of his bio, notes he is an investor in China Rapid Finance.\nhttps://www.transamerica.com/individual/why-transamerica/who-we-are/leadership/\n\n\n\nSay what you want about the viability of the operation, but these guys are vetted and certainly help the case for SOS.",
        "created_utc": 1620388467,
        "id": "gx9hl4a",
        "score": 1,
        "subreddit": "smallstreetbets",
        "created": 1620417267.0
    },
    {
        "author": "get_MEAN_yall",
        "body": "Is HPQ a buy right now??",
        "created_utc": 1622210600,
        "id": "gzrd7on",
        "score": 1,
        "subreddit": "wallstreetbets",
        "created": 1622239400.0
    },
    {
        "author": "Sisaroth",
        "body": "Depends on which news though, sure you now have news of chip shortage and gpu/laptop shortages now. Linus made a video end of februari last year 'buy a pc now'. If you took that as investing advice you would probably be up quite a lot. NVDA doubled since then, AMD +80%. INTC stagnated. ASUS doubled. ACER up 120%. Dell up 150%. HPQ doubled.",
        "created_utc": 1620418453,
        "id": "gxbafyn",
        "score": 1,
        "subreddit": "investing",
        "created": 1620447253.0
    },
    {
        "author": "Coffeepillow",
        "body": "HPQ is consistently the only good stock I own. I should just put everything into that.",
        "created_utc": 1620331058,
        "id": "gx6uuoj",
        "score": 1,
        "subreddit": "wallstreetbets",
        "created": 1620359858.0
    },
    {
        "author": "Danofireleg33",
        "body": "I do indeed. I'm currently going long term in tech such as HPQ and AMD and I've been day trading in the steel and retail apparel sectors with MT and ZEUS for steel and LEVI and HBI for retail apparel. I'm not going to post my numbers (I don't like to kiss and tell lol) but you can rest assured there is more green than red in my portfolio",
        "created_utc": 1621473930,
        "id": "gyrq4b3",
        "score": 1,
        "subreddit": "stocks",
        "created": 1621502730.0
    },
    {
        "author": "Jy_sunny",
        "body": "Buy the HPQ dip",
        "created_utc": 1622221520,
        "id": "gzs2hd4",
        "score": 1,
        "subreddit": "wallstreetbets",
        "created": 1622250320.0
    },
    {
        "author": "jkbpttrsn",
        "body": "Playing HPQ earnings. Hopefully they miss their earnings so I can moon :) cause apparently beating them is a disappointment",
        "created_utc": 1622133934,
        "id": "gznl87a",
        "score": 1,
        "subreddit": "wallstreetbets",
        "created": 1622162734.0
    },
    {
        "author": "Illustrious-Access29",
        "body": "Somebody knows why hpq is not reporting earnings yet ?? The time scheduled was 9am!!!!!!!!!!!!\ud83d\ude20\ud83d\ude20\ud83d\ude20\ud83d\ude20",
        "created_utc": 1622123275,
        "id": "gzmwoi3",
        "score": 1,
        "subreddit": "wallstreetbets",
        "created": 1622152075.0
    },
    {
        "author": "Robot_of_Sherwood",
        "body": "# Today is Monday, the 24th of May\n\n\n\n## Upcoming events for Monday, May 24th\n\n - Stock splits:\n\n    - CTUY @ **105:100** (Payable date: 06/08/2021)\n    - IAU @ **1:2**\n\n - Expected earnings:\n\n  AESE, AGBA, ALAC, ALUS, API, ARCE, ATXI, BPT, BSGM, CRMT, CRT, CYCN, ENIC, ENLV, ENOB, GSMG, GTH, LMPX, MICT, MVO, NAT, NDSN, NEW, NEXT, ONVO, PBT, PHGE, PME, PSTI, PVL, RIDE, RVPH, SJT, TH, THCA, THCB, TPHS, VOC, YQ, ZY\n\n - Ex-div:\n\n  BKR, CDW, CRAI, E, EFX, FLMN, FMS, HCAP, HNNA, JNJ, JRSH, LOB, NDSN, PRU, RHI, SPOK, SWCH, TS, WLK, XPER, YUMC\n\n - Economic events and announcements:\n\n    - 3-Month Bill Auction (previous: 0.015%)\n    - 6-Month Bill Auction (previous: 0.030%)\n    - Chicago Fed National Activity (previous: 1.71)\n    - FOMC Member Bostic Speaks\n    - FOMC Member Brainard Speaks\n    - Investing.com Gold Index (actual: 55.1%, previous: 59.9%)\n    - Investing.com S&amp;P 500 Index (actual: 45.6%, previous: 42.1%)\n\n## Upcoming events for Tuesday, May 25th\n\n - Stock splits:\n\n    - GLDFF @ **1:23**\n    - NSRCF @ **1:10**\n    - UXI @ **4:1** (Payable date: 05/24/2021)\n    - DIG @ **2:1** (Payable date: 05/24/2021)\n    - QLD @ **2:1** (Payable date: 05/24/2021)\n    - UWM @ **2:1** (Payable date: 05/24/2021)\n    - USD @ **4:1** (Payable date: 05/24/2021)\n    - SAA @ **5:1** (Payable date: 05/24/2021)\n    - UDOW @ **2:1** (Payable date: 05/24/2021)\n    - SMN @ **1:2**\n    - SZK @ **1:2**\n    - RXD @ **1:2**\n    - SIJ @ **1:2**\n    - MZZ @ **1:2**\n    - BZQ @ **1:2**\n    - SRS @ **1:2**\n    - SSG @ **1:4**\n    - SDD @ **1:4**\n    - UMDD @ **5:1** (Payable date: 05/24/2021)\n    - SDOW @ **1:4**\n    - SMDD @ **1:4**\n\n - Expected earnings:\n\n  A, ANVS, ASND, AVAH, AZO, BNR, BTX, CARV, CBRL, CNF, CSWC, CTRN, CYD, DV, DY, ESLT, FINV, GASS, HEI, HEI.A, HTHT, HTOO, IMBI, INTU, ITRN, JAN, JWN, KRKR, KTCC, LOOP, MMYT, QD, RAMP, RRGB, SCPE, SKY, SOL, STEP, STG, TEDU, TIGR, TIMB, TMCI, TOL, TRIB, URBN, VNET, VSAT, ZS\n\n - Ex-div:\n\n  AMCR, ARMK, BPOP, FBP, ITUB, JACK, L, NMRK, RE, RM, SPGI, TER, TRU, VOYA\n\n - Economic events and announcements:\n\n    - 3-Month Bill Auction (previous: 0.015%)\n    - 6-Month Bill Auction (previous: 0.030%)\n    - Chicago Fed National Activity (previous: 1.71)\n    - FOMC Member Bostic Speaks\n    - FOMC Member Brainard Speaks\n    - Investing.com Gold Index (actual: 55.1%, previous: 59.9%)\n    - Investing.com S&amp;P 500 Index (actual: 45.6%, previous: 42.1%)\n\n## Upcoming events for Wednesday, May 26th\n\n - Stock splits:\n\n    - UVXY @ **1:10**\n    - VIXY @ **1:4**\n    - SCO @ **1:4**\n    - ZSL @ **1:4**\n\n - Expected earnings:\n\n  AEO, AGL, ANF, APPS, BBAR, BBW, BLRX, BMO, BQ, CANG, CHNG, CLGN, CMCO, CMRE, CPRI, CRVL, CVCO, DBI, DKS, DXC, ELF, ESEA, EVGN, GOTU, GRIN, HLG, HMG, HOTH, ICLK, LAIX, LI, MESO, MOD, NESR, NFH, NTNX, NVDA, NVIV, NXGN, OKTA, OOMA, PATI, PDD, PLAB, PSTG, PTNR, QADA, QADB, QMCO, REX, SFET, SINT, SJ, SNOW, TBLT, UCL, UHAL, UVV, VISL, VTOL, VTRU, WDAY, WSM, ZUO\n\n - Ex-div:\n\n  ACCO, AMAT, AVA, B, CHE, CTB, DAC, FWRD, IP, JBT, KNSL, MTRN, PSEC, SMG, XYL\n\n - Economic events and announcements:\n\n    - 5-Year Note Auction (previous: 0.849%)\n    - Crude Oil Imports (previous: -0.587M)\n    - Crude Oil Inventories (previous: 1.321M)\n    - Cushing Crude Oil Inventories (previous: -0.142M)\n    - Distillate Fuel Production (previous: -0.102M)\n    - EIA Refinery Crude Runs  (previous: 0.096M)\n    - EIA Weekly Distillates Stocks (previous: -2.324M)\n    - EIA Weekly Refinery Utilization Rates (previous: 0.2%)\n    - Gasoline Inventories (previous: -1.963M)\n    - Gasoline Production (previous: 0.165M)\n    - Heating Oil Stockpiles (previous: -0.164M)\n    - MBA 30-Year Mortgage Rate (previous: 3.15%)\n    - MBA Mortgage Applications (previous: 1.2%)\n    - MBA Purchase Index (previous: 265.3)\n    - Mortgage Market Index (previous: 724.2)\n    - Mortgage Refinance Index (previous: 3,413.3)\n\n## Upcoming events for Thursday, May 27th\n\n - Expected earnings:\n\n  ADIL, ADSK, AFYA, AMWD, ATHM, BBY, BOSC, BOX, BURL, CCEP, CDZI, CELC, CETX, CIH, CKX, CM, COST, CRM, DELL, DG, DLTR, DOMO, DYAI, EBR, EBR.B, FANH, GCO, GNPX, GPS, GRNQ, HHR, HLNE, HMLP, HPQ, HWCC, ISUN, JOBS, KRT, LAZY, LBPS, LGF.A, LGF.B, MACK, MAGS, MDRR, MDT, MIXT, MOMO, MOV, MYSZ, NUZE, NVGS, OFED, OLLI, PBFS, PBR.A, PLAN, PLUG, PRPO, PRVA, QFIN, RBCN, RDHL, RY, RYB, SAFM, SBR, SEEL, SHSP, SKM, SUNW, SUPV, TD, TDAC, THR, TITN, ULTA, VEEV, VIOT, VMW, YEXT, YTRA, YY\n\n - Ex-div:\n\n  ABTX, ADC, ADI, AGNC, ALTM, ALV, AVAL, AY, BEPC, BIPC, BMI, BOH, BRMK, CATY, CBT, CFR, CPF, CR, CRT, CSX, CTT, DD, DNP, DOV, DOW, EAF, EFC, EL, EVR, FBHS, FT, FTV, FXNC, GLW, HII, HQH, HUBB, J, JKHY, KHC, KINS, MAIN, MARPS, MAS, MKSI, MLAB, MLHR, NBHC, NNI, NUS, NWL, ORC, PBT, PDM, PFIS, PIPR, POWI, PRT, PTVE, RLI, RS, SBLK, SCL, SCM, SGC, SJT, STAG, STE, STRA, TNC, TSLX, TV, UBOH, UNP, VMC, VVV, WEYS, WHD, YUM\n\n - Economic events and announcements:\n\n    - 4-Week Bill Auction (previous: 0.000%)\n    - 7-Year Note Auction (previous: 1.306%)\n    - 8-Week Bill Auction (previous: 0.005%)\n    - Continuing Jobless Claims (consensus: 3,640K, previous: 3,751K)\n    - Core Durable Goods Orders (consensus: 0.7%, previous: 2.3%)\n    - Core PCE Prices (consensus: 2.30%, previous: 2.30%)\n    - Corporate Profits (previous: 27.0%)\n    - Durable Goods Orders (consensus: 0.7%, previous: 1.0%)\n    - Durables Excluding Defense (previous: 1.8%)\n    - GDP (consensus: 6.5%, previous: 6.4%)\n    - GDP Price Index (consensus: 4.1%, previous: 4.1%)\n    - GDP Sales (previous: 9.2%)\n    - Goods Orders Non Defense Ex Air (consensus: 0.5%, previous: 1.0%)\n    - Initial Jobless Claims (consensus: 425K, previous: 444K)\n    - Jobless Claims 4-Week Avg. (previous: 504.75K)\n    - KC Fed Composite Index (previous: 31)\n    - KC Fed Manufacturing Index (previous: 40)\n    - Natural Gas Storage (previous: 71B)\n    - PCE Prices (previous: 3.5%)\n    - Pending Home Sales (consensus: 1.1%, previous: 1.9%)\n    - Pending Home Sales Index (previous: 111.3)\n    - Real Consumer Spending (previous: 10.7%)\n\n^^^^2021-05-24",
        "created_utc": 1621850413,
        "id": "gz99lv0",
        "score": 1,
        "subreddit": "RobinHood",
        "created": 1621879213.0
    },
    {
        "author": "HFClBrI",
        "body": "I literally made a program that graphs P/L for multiple different options and use them regularly to hedge my investment like with HPQ before the earning call (which saved me ~500$).\n\nI don't use options to bet like some people do.",
        "created_utc": 1622436750,
        "id": "h01uk78",
        "score": 0,
        "subreddit": "stocks",
        "created": 1622465550.0
    },
    {
        "author": "Mack_Guyver",
        "body": "PYR, CYM, HPQ, GDNP, HITI, TD",
        "created_utc": 1620848774,
        "id": "gxw5jzp",
        "score": 0,
        "subreddit": "CanadianInvestor",
        "created": 1620877574.0
    },
    {
        "author": "tooo_spicy",
        "body": "&gt;HPQ\n\nwhat is happening?",
        "created_utc": 1620323781,
        "id": "gx6d90t",
        "score": 0,
        "subreddit": "CanadianInvestor",
        "created": 1620352581.0
    },
    {
        "author": "beenabroker",
        "body": "How did they expire 1-22???\nWhen it's 5-29-21 right now u lost me cause I have CVS,PLTR,HPQ&amp; NIO\nJAN 22 leaps &amp; there still there trading away up big on CVS BOUGHT 85S AROUND 2 MONTHS ago when it was 70ish \nWhat am I missing here \n\ud83e\udda7\ud83e\udd8d help a Ape out will ya!!!\nI did make bonehead move of the century this week put 1k in short term amc puts when it was around $20 --if I bought 1k of the calls expiring yest my 1k would be worth 20-30k depending where I got out!!!! Another typical move!!! Was a 4mg Xanax night last night!!\nGood luck fellow apes stay strong!!!!",
        "created_utc": 1622304179,
        "id": "gzvrpy2",
        "score": 0,
        "subreddit": "wallstreetbets",
        "created": 1622332979.0
    },
    {
        "author": "Shamizzle",
        "body": "Anyone else playing an HPQ rebound after they knocked earnings out of the park and their price tanked?  Picked up some calls friday afternoon, and I'm hoping to be green by wednesday",
        "created_utc": 1622401159,
        "id": "h0033vn",
        "score": 0,
        "subreddit": "wallstreetbets",
        "created": 1622429959.0
    },
    {
        "author": "lanchadecancha",
        "body": "If Apple would release a straight up cheap work computer I imagine a lot of corporations would start implementing them on the business side of the market.  My company uses iPads and iPhones for all work phone and tablets, yet we are stuck with f---cking Hewlett Packard for laptops because Apple doesn't offer a basic cheap work computer for day-to-day office work.",
        "created_utc": 1622273119,
        "id": "gzumcst",
        "score": -5,
        "subreddit": "investing",
        "created": 1622301919.0
    }
]